concretefhe_lib-0.0.10-py3.9-nspkg.pth
concretefhe/lib/__init__.py
concretefhe/lib/file.py
concretefhe_lib-0.0.10.dist-info/LICENSE
concretefhe_lib-0.0.10.dist-info/METADATA
concretefhe_lib-0.0.10.dist-info/WHEEL
concretefhe_lib-0.0.10.dist-info/namespace_packages.txt
concretefhe_lib-0.0.10.dist-info/top_level.txt
concretefhe_lib-0.0.10.dist-info/RECORD
